simple_twitch_chat_listener/__init__.py
simple_twitch_chat_listener/_version.py
simple_twitch_chat_listener-0.2.1.dist-info/LICENCE
simple_twitch_chat_listener-0.2.1.dist-info/METADATA
simple_twitch_chat_listener-0.2.1.dist-info/WHEEL
simple_twitch_chat_listener-0.2.1.dist-info/top_level.txt
simple_twitch_chat_listener-0.2.1.dist-info/RECORD
