Metadata-Version: 2.1
Name: simple-twitch-chat-listener
Version: 0.2.1
Summary: Very simple to use Twitch chat bot for lurking chat that does not require an oauth token
License: MIT
Project-URL: Repository, https://github.com/goldenbeasty/simple-twitch-chat-listener
Classifier: License :: OSI Approved :: MIT License
Classifier: Operating System :: OS Independent
Classifier: Programming Language :: Python :: 3
Classifier: Topic :: Communications :: Chat :: Internet Relay Chat
License-File: LICENCE
Requires-Dist: websockets
